practice exam/Exam2/q1/q1.v
// Netflix has been engaged by movie studios to advertise new movies.
// Netflix will show visitors one of 4 ads based on the kind of movie
// they last watched.

// The following characteristics of the last watched movie are
// considered:
// - Whether the movie was animated? (A = 1 means the movie was
//     animated; otherwise A = 0)
// - Whether the starring actor was female (F = 1) or male (F = 0)?
// - The type of movie: (T = 2'b00 (action movie), 2'b01 (romance),
//     2'b10 (comedy), 2'b11 (thriller))

// The ad served is chosen by the following rules:
// - "A Good Day to Die Hard" (M = 2'b00) will be shown to viewers of
//     action movies and thrillers, unless they are animated or had a
//     female starring actor.
// - "Safe Haven" (M = 2'b01) will be selected for people who had
//     viewed romance movies or movies with a female starring actor that
//     are not comedies.
// - When the previous two movie ads aren't shown, "Escape from Planet
//     Earth" (M = 2'b10) will be shown to people viewing animated movies,
//     comedies, or action movies.
// - Otherwise, "Saving Lincoln" (M = 2'b11) will be shown.

module movies(M, A, F, T);
   output [1:0] M;
   input  	A, F;
   input  [1:0]	T;	
	wire action, romance, comedy, thriller;
	wire goodday, safe,escape,saving;
	assign	action=~T[0]&~T[1];
	assign romance=T[0]&~T[1];
	assign comedy=~T[0]&T[1];
	assign thriller=T[0]&T[1];
		
	assign goodday=(action|thriller)&~F&~A;
	assign safe= romance|(F&~comedy);
	assign escape=~goodday&~safe&(A|action|comedy);
	assign saving=~(goodday|safe|escape);
   	
	assign M[0]=safe|saving;
	assign M[1]=escape|saving;
	//or o1(M[0],safe,saving);
	//or o2(M[1],escape,saving);

endmodule // movies

practice exam/Exam2/q1/q1_tb.v
module test;

   // these are inputs to "circuit under test"
   reg       A;
   reg       F;
   reg [1:0] T;
  // wires for the outputs of "circuit under test"
   wire [1:0] M;
  // the circuit under test
   movies m(M, A, F, T);  
    
   initial begin               // initial = run at beginning of simulation
                               // begin/end = associate block with initial
      
      $dumpfile("test.vcd");  // name of dump file to create
      $dumpvars(0, test);     // record all signals of module "test" and sub-modules
                              // remember to change "test" to the correct
                              // module name when writing your own test benches
        
      // test all input combinations
      A = 0; F = 0; T = 0; #10;
      A = 0; F = 0; T = 1; #10;
      A = 0; F = 0; T = 2; #10;
      A = 0; F = 0; T = 3; #10;
      A = 0; F = 1; T = 0; #10;
      A = 0; F = 1; T = 1; #10;
      A = 0; F = 1; T = 2; #10;
      A = 0; F = 1; T = 3; #10;
      A = 1; F = 0; T = 0; #10;
      A = 1; F = 0; T = 1; #10;
      A = 1; F = 0; T = 2; #10;
      A = 1; F = 0; T = 3; #10;
      A = 1; F = 1; T = 0; #10;
      A = 1; F = 1; T = 1; #10;
      A = 1; F = 1; T = 2; #10;
      A = 1; F = 1; T = 3; #10;
      
      $finish;        // end the simulation
   end                      
   
   initial begin
     $display("inputs = A, F, T  outputs = M");
     $monitor("inputs = %b  %b  %b  outputs = %b   time = %2t",
              A, F, T, M, $time);
   end
endmodule // test

practice exam/Exam2/q1/test.vcd
$date
	Sun Feb  5 16:57:01 2017
$end
$version
	Icarus Verilog
$end
$timescale
	1s
$end
$scope module test $end
$var wire 2 ! M [1:0] $end
$var reg 1 " A $end
$var reg 1 # F $end
$var reg 2 $ T [1:0] $end
$scope module m $end
$var wire 1 % A $end
$var wire 1 & F $end
$var wire 2 ' M [1:0] $end
$var wire 2 ( T [1:0] $end
$var wire 1 ) action $end
$var wire 1 * comedy $end
$var wire 1 + escape $end
$var wire 1 , goodday $end
$var wire 1 - romance $end
$var wire 1 . safe $end
$var wire 1 / saving $end
$var wire 1 0 thriller $end
$upscope $end
$upscope $end
$enddefinitions $end
#0
$dumpvars
00
0/
0.
0-
1,
0+
0*
1)
b0 (
b0 '
0&
0%
b0 $
0#
0"
b0 !
$end
#10
0,
b1 !
b1 '
0)
1.
1-
b1 $
b1 (
#20
1+
0/
b10 !
b10 '
0.
1*
0-
b10 $
b10 (
#30
b0 !
b0 '
0+
1,
0*
10
b11 $
b11 (
#40
1)
0,
b1 !
b1 '
00
1.
b0 $
b0 (
1#
1&
#50
0)
1-
b1 $
b1 (
#60
1+
0/
b10 !
b10 '
0.
1*
0-
b10 $
b10 (
#70
0/
1.
b1 !
b1 '
0+
0*
10
b11 $
b11 (
#80
1+
0/
1)
b10 !
b10 '
00
0.
b0 $
b0 (
0#
0&
1"
1%
#90
0+
b1 !
b1 '
0)
1.
1-
b1 $
b1 (
#100
1+
0/
b10 !
b10 '
0.
1*
0-
b10 $
b10 (
#110
0*
10
b11 $
b11 (
#120
0+
1)
b1 !
b1 '
00
1.
b0 $
b0 (
1#
1&
#130
0)
1-
b1 $
b1 (
#140
1+
0/
b10 !
b10 '
0.
1*
0-
b10 $
b10 (
#150
0+
b1 !
b1 '
1.
0*
10
b11 $
b11 (
