Lab1/blackbox.v
module blackbox(l, s, i, w);
    output l;
    input  s, i, w;
    wire   w01, w07, w08, w15, w25, w31, w33, w42, w48, w49, w52, w58, w60, w63, w64, w67, w72, w80, w82, w85, w91, w92, w96;
    or  o88(l, w63, w92, w80);
    and a79(w63, w52, w60, w48);
    not n93(w48, w25);
    and a78(w92, w60, w25, w52);
    and a90(w80, w01, w07);
    not n53(w01, w60);
    or  o26(w07, w15, w58);
    and a43(w15, w52, w25);
    and a68(w58, w42, w52);
    not n81(w42, w25);
    and a65(w60, i, w82);
    or  o94(w82, w, s);
    and a71(w25, w67, w31);
    not n4(w67, s);
    or  o35(w31, w85, w72);
    not n21(w85, w);
    and a3(w72, i, w33);
    not n62(w33, i);
    or  o41(w52, w08, w96);
    and a97(w08, w64, w49);
    not n61(w64, i);
    not n5(w49, s);
    and a34(w96, w91, w, i);
    not n18(w91, s);
endmodule // blackbox

Lab1/blackbox_tb.v
module blackbox_test;

    reg s_in, i_in, w_in;                           // these are inputs to "circuit under test"
                                              // use "reg" not "wire" so can assign a value
    wire l_out;                        // wires for the outputs of "circuit under test"

    blackbox b1 (l_out, s_in, i_in, w_in);  // the circuit under test
    
    initial begin                             // initial = run at beginning of simulation
                                              // begin/end = associate block with initial
 
        $dumpfile("b.vcd");                  // name of dump file to create
        $dumpvars(0,blackbox_test);                 // record all signals of module "sc_test" and sub-modules
                                              // remember to change "sc_test" to the correct
                                              // module name when writing your own test benches
        
        // test all four input combinations
        // remember that 2 inputs means 2^2 = 4 combinations
        // 3 inputs would mean 2^3 = 8 combinations to test, and so on
        // this is very similar to the input columns of a truth table
        s_in = 0; i_in = 0; w_in = 0; # 10;             // set initial values and wait 10 time units
        s_in = 0; i_in = 0; w_in = 1; # 10;             // change inputs and then wait 10 time units
        s_in = 0; i_in = 1; w_in = 0; # 10;             // as above
        s_in = 0; i_in = 1; w_in = 1; # 10;
        s_in = 1; i_in = 0; w_in = 0; # 10;
        s_in = 1; i_in = 0; w_in = 1; # 10;
        s_in = 1; i_in = 1; w_in = 0; # 10;
        s_in = 1; i_in = 1; w_in = 1; # 10;
 
        $finish;                              // end the simulation
    end                      
    
    initial
        $monitor("At time %2t, s_in = %d i_in = %d w_in = %d l_out = %d",
                 $time, s_in, i_in, w_in, l_out);
endmodule // blackbox_test

Lab1/b.vcd
$date
	Tue Jan 24 16:57:46 2017
$end
$version
	Icarus Verilog
$end
$timescale
	1s
$end
$scope module blackbox_test $end
$var wire 1 ! l_out $end
$var reg 1 " i_in $end
$var reg 1 # s_in $end
$var reg 1 $ w_in $end
$scope module b1 $end
$var wire 1 % i $end
$var wire 1 ! l $end
$var wire 1 & s $end
$var wire 1 ' w $end
$var wire 1 ( w01 $end
$var wire 1 ) w07 $end
$var wire 1 * w08 $end
$var wire 1 + w15 $end
$var wire 1 , w25 $end
$var wire 1 - w31 $end
$var wire 1 . w33 $end
$var wire 1 / w42 $end
$var wire 1 0 w48 $end
$var wire 1 1 w49 $end
$var wire 1 2 w52 $end
$var wire 1 3 w58 $end
$var wire 1 4 w60 $end
$var wire 1 5 w63 $end
$var wire 1 6 w64 $end
$var wire 1 7 w67 $end
$var wire 1 8 w72 $end
$var wire 1 9 w80 $end
$var wire 1 : w82 $end
$var wire 1 ; w85 $end
$var wire 1 < w91 $end
$var wire 1 = w92 $end
$var wire 1 > w96 $end
$upscope $end
$upscope $end
$enddefinitions $end
#0
$dumpvars
0>
0=
1<
1;
0:
19
08
17
16
05
04
03
12
11
00
0/
1.
1-
1,
1+
1*
1)
1(
0'
0&
0%
0$
0#
0"
1!
$end
#10
1!
19
13
1)
1/
0+
10
0,
0-
1:
0;
1$
1'
#20
0)
0/
00
0!
03
1,
09
02
1-
1(
05
0*
0:
1;
04
0.
06
0$
0'
1"
1%
#30
13
15
1/
10
1)
1!
0(
0,
0+
0=
14
0-
12
1:
0;
1>
1$
1'
#40
0)
09
0!
03
1-
1(
05
02
1;
04
1.
16
0>
07
01
0<
0$
0'
0"
0%
1#
1&
#50
0-
0;
1$
1'
#60
1-
0(
1;
14
0.
06
0$
0'
1"
1%
#70
0-
0;
1$
1'
