Lab5/decoder.v
// mips_decode: a decoder for MIPS arithmetic instructions
//
// alu_op      (output) - control signal to be sent to the ALU
// writeenable (output) - should a new value be captured by the register file
// rd_src      (output) - should the destination register be rd (0) or rt (1)
// alu_src2    (output) - should the 2nd ALU source be a register (0) or an immediate (1)
// except      (output) - set to 1 when the opcode/funct combination is unrecognized
// opcode      (input)  - the opcode field from the instruction
// funct       (input)  - the function field from the instruction
//

module mips_decode(alu_op, writeenable, rd_src, alu_src2, except, opcode, funct);
    output [2:0] alu_op;
    output       writeenable, rd_src, alu_src2, except;
    input  [5:0] opcode, funct;
	
	wire r =opcode==`OP_OTHER0;
	wire addi=opcode==`OP_ADDI;
	wire andi=opcode==`OP_ANDI;
	wire ori=opcode==`OP_ORI;
	wire xori=opcode==`OP_XORI;
	wire add=r&(funct==`OP0_ADD);
	wire sub=r&(funct==`OP0_SUB);
	wire myand=r&(funct==`OP0_AND);
	wire myor=r&(funct==`OP0_OR);
	wire mynor=r&(funct==`OP0_NOR);
	wire myxor=r&(funct==`OP0_XOR);
	assign writeenable=(addi|andi|ori|xori|add|sub|myand|myor|mynor|myxor);
	assign except=~writeenable;
	assign rd_src=(addi|andi|ori|xori);
	assign alu_src2=(addi|andi|ori|xori);
	assign alu_op[0]=(sub|myor|myxor|ori|xori);
	assign alu_op[1]=(add|sub|mynor|myxor|addi|xori);
	assign alu_op[2]=(myand|myor|mynor|myxor|andi|ori|xori);
endmodule // mips_decode

Lab6/decoder_tb.v
module decoder_test;
    reg [5:0] opcode, funct;
    reg       zero  = 0;

    initial begin
        $dumpfile("decoder.vcd");
        $dumpvars(0, decoder_test);

        // remember that all your instructions from last week should still work
             opcode = `OP_OTHER0; funct = `OP0_ADD; // see if addition still works
        # 10 opcode = `OP_OTHER0; funct = `OP0_SUB; // see if subtraction still works
        // test all of the others here
        # 10 opcode = `OP_OTHER0; funct = `OP0_AND;
		# 10 opcode = `OP_OTHER0; funct = `OP0_OR;
		# 10 opcode = `OP_OTHER0; funct = `OP0_NOR;
		# 10 opcode = `OP_OTHER0; funct = `OP0_XOR;
		# 10 opcode = `OP_ADDI;
		# 10 opcode = `OP_ANDI;
		# 10 opcode = `OP_ORI;
		# 10 opcode = `OP_XORI;
        // as should all the new instructions from this week
        # 10 opcode = `OP_BEQ; zero = 0; // try a not taken beq
        # 10 opcode = `OP_BEQ; zero = 1; // try a taken beq
        # 10 opcode = `OP_BNE; zero = 0; 
        # 10 opcode = `OP_BNE; zero = 1;
        # 10 opcode = `OP_J; 
        # 10 opcode = `OP_OTHER0; funct =`OP0_JR; 
        # 10 opcode = `OP_LUI; 
        # 10 opcode = `OP_OTHER0; funct =`OP0_SLT; 
        # 10 opcode = `OP_LW; 
        # 10 opcode = `OP_LBU;
        # 10 opcode = `OP_SW;
        # 10 opcode = `OP_SB;
        # 10 opcode = `OP_OTHER0; funct = `OP0_ADDM;
        // add more tests here!

        # 10 $finish;
    end

    // use gtkwave to test correctness
    wire [2:0] alu_op;
    wire       writeenable, rd_src, alu_src2, except;
    wire [1:0] control_type;
    wire       mem_read, word_we, byte_we, byte_load, lui, slt, addm;
    mips_decode decoder(alu_op, writeenable, rd_src, alu_src2, except, control_type,
                        mem_read, word_we, byte_we, byte_load, lui, slt, addm,
                        opcode, funct, zero);
endmodule // decoder_test

Lab5/decoder.vcd
$date
	Sat Feb 18 16:02:43 2017
$end
$version
	Icarus Verilog
$end
$timescale
	1s
$end
$scope module decoder_test $end
$var wire 3 ! alu_op [2:0] $end
$var wire 1 " alu_src2 $end
$var wire 1 # except $end
$var wire 1 $ rd_src $end
$var wire 1 % writeenable $end
$var reg 6 & funct [5:0] $end
$var reg 6 ' opcode [5:0] $end
$scope module decoder $end
$var wire 1 ( add $end
$var wire 1 ) addi $end
$var wire 3 * alu_op [2:0] $end
$var wire 1 " alu_src2 $end
$var wire 1 + andi $end
$var wire 1 # except $end
$var wire 6 , funct [5:0] $end
$var wire 1 - myand $end
$var wire 1 . mynor $end
$var wire 1 / myor $end
$var wire 1 0 myxor $end
$var wire 6 1 opcode [5:0] $end
$var wire 1 2 ori $end
$var wire 1 3 r $end
$var wire 1 $ rd_src $end
$var wire 1 4 sub $end
$var wire 1 % writeenable $end
$var wire 1 5 xori $end
$upscope $end
$upscope $end
$enddefinitions $end
#0
$dumpvars
05
04
13
02
b0 1
00
0/
0.
0-
b100000 ,
0+
b10 *
0)
1(
b0 '
b100000 &
1%
0$
0#
0"
b10 !
$end
#10
b11 !
b11 *
0(
14
b100010 &
b100010 ,
#20
b100 !
b100 *
04
1-
b100100 &
b100100 ,
#30
b101 !
b101 *
0-
1/
b100101 &
b100101 ,
#40
b110 !
b110 *
0/
1.
b100111 &
b100111 ,
#50
b111 !
b111 *
0.
10
b100110 &
b100110 ,
#60
b10 !
b10 *
0#
1"
1$
1%
00
b1000 '
b1000 1
03
1)
#70
b100 !
b100 *
b1100 '
b1100 1
0)
1+
#80
b101 !
b101 *
b1101 '
b1101 1
0+
12
#90
b111 !
b111 *
b1110 '
b1110 1
02
15
#100
1#
0%
b0 !
b0 *
0"
0$
b100100 &
b100100 ,
b1 '
b1 1
05
