Lab6/decoder.v
// mips_decode: a decoder for MIPS arithmetic instructions
//
// alu_op       (output) - control signal to be sent to the ALU
// writeenable  (output) - should a new value be captured by the register file
// rd_src       (output) - should the destination register be rd (0) or rt (1)
// alu_src2     (output) - should the 2nd ALU source be a register (0) or an immediate (1)
// except       (output) - set to 1 when we don't recognize an opdcode & funct combination
// control_type (output) - 00 = fallthrough, 01 = branch_target, 10 = jump_target, 11 = jump_register 
// mem_read     (output) - the register value written is coming from the memory
// word_we      (output) - we're writing a word's worth of data
// byte_we      (output) - we're only writing a byte's worth of data
// byte_load    (output) - we're doing a byte load
// lui          (output) - the instruction is a lui
// slt          (output) - the instruction is an slt
// addm         (output) - the instruction is an addm
// opcode        (input) - the opcode field from the instruction
// funct         (input) - the function field from the instruction
// zero          (input) - from the ALU
//

module mips_decode(alu_op, writeenable, rd_src, alu_src2, except, control_type,
                   mem_read, word_we, byte_we, byte_load, lui, slt, addm,
                   opcode, funct, zero);
    output [2:0] alu_op;
    output       writeenable, rd_src, alu_src2, except;
    output [1:0] control_type;
    output       mem_read, word_we, byte_we, byte_load, lui, slt, addm;
    input  [5:0] opcode, funct;
    input        zero;
	//old
	wire r =opcode==`OP_OTHER0;
	wire addi=opcode==`OP_ADDI;
	wire andi=opcode==`OP_ANDI;
	wire ori=opcode==`OP_ORI;
	wire xori=opcode==`OP_XORI;
	wire add=r&(funct==`OP0_ADD);
	wire sub=r&(funct==`OP0_SUB);
	wire myand=r&(funct==`OP0_AND);
	wire myor=r&(funct==`OP0_OR);
	wire mynor=r&(funct==`OP0_NOR);
	wire myxor=r&(funct==`OP0_XOR);
	//new
	wire bne=opcode==`OP_BNE;
	wire beq=opcode==`OP_BEQ;
	wire j=opcode==`OP_J;
	wire jr=r&(funct==`OP0_JR);
	wire LUI=opcode==`OP_LUI;
	wire SLT=r&(funct==`OP0_SLT);
	wire lw=opcode==`OP_LW;
	wire lbu=opcode==`OP_LBU;
	wire sw=opcode==`OP_SW;
	wire sb=opcode==`OP_SB;
	wire ADDM=r&(funct==`OP0_ADDM);
	assign writeenable=(addi|andi|ori|xori|add|sub|myand|myor|mynor|myxor|LUI|SLT|lw|lbu|ADDM);
	assign except=~(addi|andi|ori|xori|add|sub|myand|myor|mynor|myxor|bne|beq|j|jr|LUI|SLT|lw|lbu|sw|sb|ADDM);
	assign rd_src=(addi|andi|ori|xori|LUI|lw|lbu);
	assign alu_src2=(addi|andi|ori|xori|lw|lbu|sw|sb);
	assign alu_op[0]=(sub|myor|myxor|ori|xori|beq|bne|SLT);
	assign alu_op[1]=(add|sub|mynor|myxor|addi|xori|beq|bne|SLT|lw|lbu|sw|sb|ADDM);
	assign alu_op[2]=(myand|myor|mynor|myxor|andi|ori|xori);
	assign control_type[0]=(jr|(zero&beq)|(~zero&bne));
	assign control_type[1]=(j|jr);
	assign mem_read=(lw|lbu|ADDM);
	assign word_we=sw;
	assign byte_we=sb;
	assign byte_load=lbu;
	assign lui=LUI;
	assign slt=SLT;
	assign addm=ADDM;
endmodule // mips_decode

Lab6/decoder_tb.v
module decoder_test;
    reg [5:0] opcode, funct;
    reg       zero  = 0;

    initial begin
        $dumpfile("decoder.vcd");
        $dumpvars(0, decoder_test);

        // remember that all your instructions from last week should still work
             opcode = `OP_OTHER0; funct = `OP0_ADD; // see if addition still works
        # 10 opcode = `OP_OTHER0; funct = `OP0_SUB; // see if subtraction still works
        // test all of the others here
        # 10 opcode = `OP_OTHER0; funct = `OP0_AND;
		# 10 opcode = `OP_OTHER0; funct = `OP0_OR;
		# 10 opcode = `OP_OTHER0; funct = `OP0_NOR;
		# 10 opcode = `OP_OTHER0; funct = `OP0_XOR;
		# 10 opcode = `OP_ADDI;
		# 10 opcode = `OP_ANDI;
		# 10 opcode = `OP_ORI;
		# 10 opcode = `OP_XORI;
        // as should all the new instructions from this week
        # 10 opcode = `OP_BEQ; zero = 0; // try a not taken beq
        # 10 opcode = `OP_BEQ; zero = 1; // try a taken beq
        # 10 opcode = `OP_BNE; zero = 0; 
        # 10 opcode = `OP_BNE; zero = 1;
        # 10 opcode = `OP_J; 
        # 10 opcode = `OP_OTHER0; funct =`OP0_JR; 
        # 10 opcode = `OP_LUI; 
        # 10 opcode = `OP_OTHER0; funct =`OP0_SLT; 
        # 10 opcode = `OP_LW; 
        # 10 opcode = `OP_LBU;
        # 10 opcode = `OP_SW;
        # 10 opcode = `OP_SB;
        # 10 opcode = `OP_OTHER0; funct = `OP0_ADDM;
        // add more tests here!

        # 10 $finish;
    end

    // use gtkwave to test correctness
    wire [2:0] alu_op;
    wire       writeenable, rd_src, alu_src2, except;
    wire [1:0] control_type;
    wire       mem_read, word_we, byte_we, byte_load, lui, slt, addm;
    mips_decode decoder(alu_op, writeenable, rd_src, alu_src2, except, control_type,
                        mem_read, word_we, byte_we, byte_load, lui, slt, addm,
                        opcode, funct, zero);
endmodule // decoder_test

Lab6/decoder.vcd
$date
	Sun Mar  5 16:38:34 2017
$end
$version
	Icarus Verilog
$end
$timescale
	1s
$end
$scope module decoder_test $end
$var wire 1 ! addm $end
$var wire 3 " alu_op [2:0] $end
$var wire 1 # alu_src2 $end
$var wire 1 $ byte_load $end
$var wire 1 % byte_we $end
$var wire 2 & control_type [1:0] $end
$var wire 1 ' except $end
$var wire 1 ( lui $end
$var wire 1 ) mem_read $end
$var wire 1 * rd_src $end
$var wire 1 + slt $end
$var wire 1 , word_we $end
$var wire 1 - writeenable $end
$var reg 6 . funct [5:0] $end
$var reg 6 / opcode [5:0] $end
$var reg 1 0 zero $end
$scope module decoder $end
$var wire 1 1 ADDM $end
$var wire 1 2 LUI $end
$var wire 1 3 SLT $end
$var wire 1 4 add $end
$var wire 1 5 addi $end
$var wire 1 ! addm $end
$var wire 3 6 alu_op [2:0] $end
$var wire 1 # alu_src2 $end
$var wire 1 7 andi $end
$var wire 1 8 beq $end
$var wire 1 9 bne $end
$var wire 1 $ byte_load $end
$var wire 1 % byte_we $end
$var wire 2 : control_type [1:0] $end
$var wire 1 ' except $end
$var wire 6 ; funct [5:0] $end
$var wire 1 < j $end
$var wire 1 = jr $end
$var wire 1 > lbu $end
$var wire 1 ( lui $end
$var wire 1 ? lw $end
$var wire 1 ) mem_read $end
$var wire 1 @ myand $end
$var wire 1 A mynor $end
$var wire 1 B myor $end
$var wire 1 C myxor $end
$var wire 6 D opcode [5:0] $end
$var wire 1 E ori $end
$var wire 1 F r $end
$var wire 1 * rd_src $end
$var wire 1 G sb $end
$var wire 1 + slt $end
$var wire 1 H sub $end
$var wire 1 I sw $end
$var wire 1 , word_we $end
$var wire 1 - writeenable $end
$var wire 1 J xori $end
$var wire 1 K zero $end
$upscope $end
$upscope $end
$enddefinitions $end
#0
$dumpvars
0K
0J
0I
0H
0G
1F
0E
b0 D
0C
0B
0A
0@
0?
0>
0=
0<
b100000 ;
b0 :
09
08
07
b10 6
05
14
03
02
01
00
b0 /
b100000 .
1-
0,
0+
0*
0)
0(
0'
b0 &
0%
0$
0#
b10 "
0!
$end
#10
b11 "
b11 6
04
1H
b100010 .
b100010 ;
#20
b100 "
b100 6
0H
1@
b100100 .
b100100 ;
#30
b101 "
b101 6
0@
1B
b100101 .
b100101 ;
#40
b110 "
b110 6
0B
1A
b100111 .
b100111 ;
#50
b111 "
b111 6
0A
1C
b100110 .
b100110 ;
#60
0'
1-
1#
1*
b10 "
b10 6
0C
b1000 /
b1000 D
0F
15
#70
b100 "
b100 6
b1100 /
b1100 D
05
17
#80
b101 "
b101 6
b1101 /
b1101 D
07
1E
#90
b111 "
b111 6
b1110 /
b1110 D
0E
1J
#100
0-
0#
0*
b11 "
b11 6
b100 /
b100 D
0J
18
#110
b1 &
b1 :
10
1K
#120
0'
00
0K
b101 /
b101 D
19
08
#130
b0 &
b0 :
10
1K
#140
b0 "
b0 6
b10 &
b10 :
b10 /
b10 D
09
1<
#150
1=
b11 &
b11 :
b1000 .
b1000 ;
b0 /
b0 D
1F
0<
#160
1-
1*
b0 &
b0 :
0=
b1111 /
b1111 D
0F
12
1(
#170
0*
b11 "
b11 6
1+
13
b101010 .
b101010 ;
b0 /
b0 D
1F
02
0(
#180
1#
b10 "
b10 6
1)
1*
0+
03
b100011 /
b100011 D
0F
1?
#190
b100100 /
b100100 D
0?
1>
1$
#200
0)
0-
0*
b101011 /
b101011 D
0>
0$
1I
1,
#210
b101000 /
b101000 D
0I
0,
1G
1%
#220
1-
1)
1!
11
0#
b101100 .
b101100 ;
b0 /
b0 D
1F
0G
0%
